meson.build
pysquishy/__init__.py
pysquishy/clang.py
pysquishy/error.py
pysquishy/log.py
pysquishy/squishy.py
pysquishy-0.1.3.dist-info/LICENSE
pysquishy-0.1.3.dist-info/WHEEL
pysquishy-0.1.3.dist-info/METADATA
pysquishy-0.1.3.dist-info/RECORD
