Metadata-Version: 2.1
Name: pysquishy
Version: 0.1.3
Summary: LLVM pass wrapper library for creating robust shellcode
License: MIT
Author: novafacing
Author-email: rowanbhart@gmail.com
Requires-Python: >=3.8,<4.0
Classifier: License :: OSI Approved :: MIT License
Classifier: Programming Language :: Python :: 3
Classifier: Programming Language :: Python :: 3.8
Classifier: Programming Language :: Python :: 3.9
Classifier: Programming Language :: Python :: 3.10
Requires-Dist: coloredlogs (>=15.0.1,<16.0.0)
Requires-Dist: lief (>=0.12.1,<0.13.0)
